cefconsole/__init__.py
cefconsole/boilerplate.py
cefconsole/core.py
cefconsole/repl.py
cefconsole/templates/console.html
cefconsole/templates/demo.html
cefconsole/templates/python.html
panda3d_cefconsole-0.1.11a0.dist-info/METADATA
panda3d_cefconsole-0.1.11a0.dist-info/WHEEL
panda3d_cefconsole-0.1.11a0.dist-info/entry_points.txt
panda3d_cefconsole-0.1.11a0.dist-info/top_level.txt
panda3d_cefconsole-0.1.11a0.dist-info/RECORD
